{
  "combo": {
    "draw": "off",
    "xg": "on",
    "drift": "on",
    "clustering": "on",
    "pressure": "on",
    "tardeAsia": "off",
    "momentumXG": "off",
    "br": "fixed"
  },
  "risk_filter": "all",
  "best_score": 839.04,
  "adj": {
    "dedup": false,
    "minOdds": null,
    "maxOdds": 7.0,
    "slippagePct": 2,
    "conflictFilter": false,
    "allowContrarias": true,
    "minStability": 1,
    "driftMinMinute": null,
    "globalMinuteMin": null,
    "globalMinuteMax": null
  },
  "n_bets": 88,
  "wins": 61,
  "win_pct": 69.3,
  "flat_roi": 95.35,
  "flat_pl": 839.04,
  "ci_low": 59.0,
  "ci_high": 78.0,
  "csv_path": "C:\\Users\\agonz\\OneDrive\\Documents\\Proyectos\\Furbo\\betfair_scraper\\data\\presets\\preset_max_pl.csv",
  "config_path": "C:\\Users\\agonz\\OneDrive\\Documents\\Proyectos\\Furbo\\betfair_scraper\\data\\presets\\preset_max_pl_config.json"
}