{
  "combo": {
    "draw": "off",
    "xg": "off",
    "drift": "on",
    "clustering": "on",
    "pressure": "off",
    "tardeAsia": "off",
    "momentumXG": "off",
    "br": "fixed"
  },
  "risk_filter": "all",
  "best_score": 50.3,
  "adj": {
    "dedup": false,
    "minOdds": null,
    "maxOdds": 6.0,
    "slippagePct": 0,
    "conflictFilter": false,
    "allowContrarias": true,
    "minStability": 1,
    "driftMinMinute": 30,
    "globalMinuteMin": null,
    "globalMinuteMax": null
  },
  "n_bets": 36,
  "wins": 24,
  "win_pct": 66.7,
  "flat_roi": 7.49,
  "flat_pl": 26.98,
  "ci_low": 50.3,
  "ci_high": 79.8,
  "csv_path": "C:\\Users\\agonz\\OneDrive\\Documents\\Proyectos\\Furbo\\betfair_scraper\\data\\presets\\preset_max_wr.csv",
  "config_path": "C:\\Users\\agonz\\OneDrive\\Documents\\Proyectos\\Furbo\\betfair_scraper\\data\\presets\\preset_max_wr_config.json"
}